cimr/__init__.py
cimr/base.py
cimr/prompt.py
cimr/data/annotation/gene_grch37_gencode_v29.txt.gz
cimr/data/annotation/gene_grch38_gencode_v26.txt.gz
cimr/data/annotation/variant_grch37_subset.txt.gz
cimr/data/annotation/variant_grch38_subset.txt.gz
cimr/data/eqtl/eqtl.txt
cimr/gene/__init__.py
cimr/gene/gene_prompt.py
cimr/network/__init__.py
cimr/network/network_prompt.py
cimr/network/rwr.py
cimr/network/utils.py
cimr/processor/__init__.py
cimr/processor/processor_prompt.py
cimr/processor/query.py
cimr/processor/tad.py
cimr/processor/utils.py
cimr-0.1.3.dist-info/LICENSE.md
cimr-0.1.3.dist-info/METADATA
cimr-0.1.3.dist-info/WHEEL
cimr-0.1.3.dist-info/entry_points.txt
cimr-0.1.3.dist-info/top_level.txt
cimr-0.1.3.dist-info/RECORD
