Metadata-Version: 2.1
Name: cimr
Version: 0.1.3
Summary: continuous integration of association summary statistics for network analysis
Home-page: https://github.com/greenelab/cimr
Author: YoSon Park
Author-email: yoson.park@gmail.com
License: BSD 3-Clause
Keywords: gene network ci
Platform: UNKNOWN
Classifier: Intended Audience :: Science/Research
Classifier: Topic :: Scientific/Engineering :: Bio-Informatics
Classifier: Topic :: Scientific/Engineering :: Information Analysis
Classifier: License :: OSI Approved :: BSD License
Classifier: Programming Language :: Python :: 3
Classifier: Programming Language :: Python :: 3 :: Only
Classifier: Programming Language :: Python :: 3.6
Requires-Python: >=3.6
Requires-Dist: scikit-learn
Requires-Dist: numpy
Requires-Dist: pandas
Requires-Dist: pathlib
Requires-Dist: setuptools
Requires-Dist: requests
